first_library/__init__.py
first_library/operation.py
first_firstlibrary-0.0.1.dist-info/METADATA
first_firstlibrary-0.0.1.dist-info/WHEEL
first_firstlibrary-0.0.1.dist-info/top_level.txt
first_firstlibrary-0.0.1.dist-info/RECORD
