Metadata-Version: 2.1
Name: first-firstlibrary
Version: 0.0.1
Summary: operation & greeting library
Home-page: UNKNOWN
Author-email: felas29@gmail.com
License: UNKNOWN
Platform: UNKNOWN
